uart.v
/*
The UART that is going to transmit data receives the data from a data bus.
The data bus is used to send data to the UART by another device like a CPU,
memory, or microcontroller. Data is transferred from the data bus to the 
transmitting UART in parallel form. After the transmitting UART gets the 
parallel data from the data bus, it adds a start bit, a parity bit, and a 
stop bit, creating the data packet. Next, the data packet is output serially,
bit by bit at the Tx pin. The receiving UART reads the data packet bit by bit 
at its Rx pin. The receiving UART then converts the data back into parallel 
form and removes the start bit, parity bit, and stop bits. Finally, the receiving 
UART transfers the data packet in parallel to the data bus on the receiving end:

*/
module uart(in,out,trans);

input [7:0] in;
input trans;
output reg [7:0] out;
//Data is loaded in parallel
reg [11:0] Tx;  //Tx terminal of UART
reg [11:0] Rx;  // Rx of of receiving terminal
reg start_bit,parity_bit; // parametric bits for packet making
reg [1:0] stop_bit;
// creating data packet;

/*
start_bit is active low signal for transmission
stop bits are indicator for termination of serial data
*/
initial
begin start_bit=1; 
stop_bit=2'b11;
end

integer i;

// This is where the formation of packet takes place which will be loaded to Tx, Data will be in parallel form
always @(posedge trans)
begin
  if(trans)
   begin
     start_bit=0;
     parity_bit= ^(in)?1:0;  // Parity bit=1 if odd 0 for even no. os 1's
     Tx={start_bit,in,parity_bit,stop_bit};
   end
end

// Here the data will be transmitted to Rx of another UART in serial form
always @(negedge trans)
 begin
    for(i=0;i<12;i=i+1)
       #5 Rx[i]=Tx[i];

start_bit=1;
out=Rx[10:3];
end




endmodule



// Testbench of the given UART code


module uart_test;

reg [7:0] in;
reg trans;
wire [7:0] out;

uart uut(in,out,trans);

initial
begin

in=8'b10110010;  // data to be transferred B2
trans=0;

$dumpfile("uart_test.vcd");
$dumpvars(0,uart_test);


end

initial
begin
#30 trans=1;
#50 trans=0;
#80 trans=1;
#50 trans=0;
end
initial #119 in=8'b00100110;
initial #350 $finish;

endmodule

uart_test.vcd
$date
	Sat Jun 24 10:17:01 2023
$end
$version
	Icarus Verilog
$end
$timescale
	1s
$end
$scope module uart_test $end
$var wire 8 ! out [7:0] $end
$var reg 8 " in [7:0] $end
$var reg 1 # trans $end
$scope module uut $end
$var wire 8 $ in [7:0] $end
$var wire 1 # trans $end
$var reg 12 % Rx [11:0] $end
$var reg 12 & Tx [11:0] $end
$var reg 8 ' out [7:0] $end
$var reg 1 ( parity_bit $end
$var reg 1 ) start_bit $end
$var reg 2 * stop_bit [1:0] $end
$var integer 32 + i [31:0] $end
$upscope $end
$upscope $end
$enddefinitions $end
$comment Show the parameter values. $end
$dumpall
$end
#0
$dumpvars
b0 +
b11 *
1)
x(
bx '
bx &
bx %
b10110010 $
0#
b10110010 "
bx !
$end
#5
b1 +
#10
b10 +
#15
b11 +
#20
b100 +
#25
b101 +
#30
b10110010011 &
0(
0)
b110 +
1#
#35
b111 +
bx0xxxxxx %
#40
b1000 +
bx10xxxxxx %
#45
b1001 +
bx110xxxxxx %
#50
b1010 +
bx0110xxxxxx %
#55
b1011 +
bx10110xxxxxx %
#60
b10110xxx !
b10110xxx '
1)
b1100 +
b10110xxxxxx %
#80
b0 +
0#
#85
b1 +
b10110xxxxx1 %
#90
b10 +
b10110xxxx11 %
#95
b11 +
b10110xxx011 %
#100
b100 +
b10110xx0011 %
#105
b101 +
b10110x10011 %
#110
b110 +
b10110010011 %
#115
b111 +
#119
b100110 "
b100110 $
#120
b1000 +
#125
b1001 +
#130
b1010 +
#135
b1011 +
#140
b10110010 !
b10110010 '
b1100 +
#160
b100110111 &
1(
0)
1#
#210
b0 +
0#
#215
b1 +
#220
b10 +
#225
b11 +
b10110010111 %
#230
b100 +
#235
b101 +
#240
b110 +
b10110110111 %
#245
b111 +
#250
b1000 +
b10100110111 %
#255
b1001 +
#260
b1010 +
#265
b1011 +
b100110111 %
#270
b100110 !
b100110 '
1)
b1100 +
